{
    "name": "FireBeetle2 ESP32-S3",
    "version": "1.0.0",
    "description": "DFRobot FireBeetle2 ESP32-S3 Board",
    "compilerTool": "aily-builder",
    "core": "esp32:esp32",
    "type": "esp32:esp32:dfrobot_firebeetle2_esp32s3",
    "mode": [
        "arduino"
    ],
    "compilerParam": "compile -v -b esp32:esp32:dfrobot_firebeetle2_esp32s3",
    "uploadParam": "esptool --chip esp32s3 --port ${serial} --baud ${baud} --before default_reset --after hard_reset write_flash -z --flash_mode keep --flash_freq keep --flash_size keep 0x0 ${bootloader} 0x8000 ${partitions} 0xe000 ${boot_app0} 0x10000 ${'*.bin'}",
    "analogPins": [
        [
            "A0 (IO4)",
            "4"
        ],
        [
            "A1 (IO5)",
            "5"
        ],
        [
            "A2 (IO6)",
            "6"
        ],
        [
            "A3 (IO8)",
            "8"
        ],
        [
            "A4 (IO10)",
            "10"
        ],
        [
            "A5 (IO11)",
            "11"
        ]
    ],
    "digitalPins": [
        [
            "D2 (IO3)",
            "3"
        ],
        [
            "D3 (IO38)",
            "38"
        ],
        [
            "D6 (IO18)",
            "18"
        ],
        [
            "D7 (IO9)",
            "9"
        ],
        [
            "D12 (IO12)",
            "12"
        ],
        [
            "D13 (IO21)",
            "21"
        ],
        [
            "D14 (IO47)",
            "47"
        ],
        [
            "IO0",
            "0"
        ],
        [
            "IO1 (SDA)",
            "1"
        ],
        [
            "IO2 (SCL)",
            "2"
        ],
        [
            "IO3",
            "3"
        ],
        [
            "IO4",
            "4"
        ],
        [
            "IO5",
            "5"
        ],
        [
            "IO6",
            "6"
        ],
        [
            "IO7",
            "7"
        ],
        [
            "IO8",
            "8"
        ],
        [
            "IO9",
            "9"
        ],
        [
            "IO10",
            "10"
        ],
        [
            "IO11",
            "11"
        ],
        [
            "IO12",
            "12"
        ],
        [
            "IO13",
            "13"
        ],
        [
            "IO14",
            "14"
        ],
        [
            "IO15 (MOSI)",
            "15"
        ],
        [
            "IO16 (MISO)",
            "16"
        ],
        [
            "IO17 (SCK)",
            "17"
        ],
        [
            "IO18",
            "18"
        ],
        [
            "IO21",
            "21"
        ],
        [
            "IO38",
            "38"
        ],
        [
            "IO43 (TX)",
            "43"
        ],
        [
            "IO44 (RX)",
            "44"
        ],
        [
            "IO47",
            "47"
        ]
    ],
    "pwmPins": [
        [
            "D2 (IO3)",
            "3"
        ],
        [
            "D3 (IO38)",
            "38"
        ],
        [
            "D6 (IO18)",
            "18"
        ],
        [
            "D7 (IO9)",
            "9"
        ],
        [
            "D12 (IO12)",
            "12"
        ],
        [
            "D13 (IO21)",
            "21"
        ],
        [
            "D14 (IO47)",
            "47"
        ],
        [
            "IO0",
            "0"
        ],
        [
            "IO1 (SDA)",
            "1"
        ],
        [
            "IO2 (SCL)",
            "2"
        ],
        [
            "IO3",
            "3"
        ],
        [
            "IO4",
            "4"
        ],
        [
            "IO5",
            "5"
        ],
        [
            "IO6",
            "6"
        ],
        [
            "IO7",
            "7"
        ],
        [
            "IO8",
            "8"
        ],
        [
            "IO9",
            "9"
        ],
        [
            "IO10",
            "10"
        ],
        [
            "IO11",
            "11"
        ],
        [
            "IO12",
            "12"
        ],
        [
            "IO13",
            "13"
        ],
        [
            "IO14",
            "14"
        ],
        [
            "IO15 (MOSI)",
            "15"
        ],
        [
            "IO16 (MISO)",
            "16"
        ],
        [
            "IO17 (SCK)",
            "17"
        ],
        [
            "IO18",
            "18"
        ],
        [
            "IO21",
            "21"
        ],
        [
            "IO38",
            "38"
        ],
        [
            "IO43 (TX)",
            "43"
        ],
        [
            "IO44 (RX)",
            "44"
        ],
        [
            "IO47",
            "47"
        ]
    ],
    "servoPins": [
        [
            "D2 (IO3)",
            "3"
        ],
        [
            "D3 (IO38)",
            "38"
        ],
        [
            "D6 (IO18)",
            "18"
        ],
        [
            "D7 (IO9)",
            "9"
        ],
        [
            "D12 (IO12)",
            "12"
        ],
        [
            "D13 (IO21)",
            "21"
        ],
        [
            "D14 (IO47)",
            "47"
        ],
        [
            "IO0",
            "0"
        ],
        [
            "IO1 (SDA)",
            "1"
        ],
        [
            "IO2 (SCL)",
            "2"
        ],
        [
            "IO3",
            "3"
        ],
        [
            "IO4",
            "4"
        ],
        [
            "IO5",
            "5"
        ],
        [
            "IO6",
            "6"
        ],
        [
            "IO7",
            "7"
        ],
        [
            "IO8",
            "8"
        ],
        [
            "IO9",
            "9"
        ],
        [
            "IO10",
            "10"
        ],
        [
            "IO11",
            "11"
        ],
        [
            "IO12",
            "12"
        ],
        [
            "IO13",
            "13"
        ],
        [
            "IO14",
            "14"
        ],
        [
            "IO15 (MOSI)",
            "15"
        ],
        [
            "IO16 (MISO)",
            "16"
        ],
        [
            "IO17 (SCK)",
            "17"
        ],
        [
            "IO18",
            "18"
        ],
        [
            "IO21",
            "21"
        ],
        [
            "IO38",
            "38"
        ],
        [
            "IO43 (TX)",
            "43"
        ],
        [
            "IO44 (RX)",
            "44"
        ],
        [
            "IO47",
            "47"
        ]
    ],
    "serialPort": [
        [
            "Serial",
            "Serial"
        ],
        [
            "Serial1",
            "Serial1"
        ],
        [
            "Serial2",
            "Serial2"
        ]
    ],
    "serialSpeed": [
        [
            "1200",
            "1200"
        ],
        [
            "9600",
            "9600"
        ],
        [
            "14400",
            "14400"
        ],
        [
            "19200",
            "19200"
        ],
        [
            "38400",
            "38400"
        ],
        [
            "57600",
            "57600"
        ],
        [
            "115200",
            "115200"
        ]
    ],
    "spi": [
        [
            "SPI",
            "SPI"
        ]
    ],
    "spiPins": {
        "SPI": [
            [
                "MOSI",
                "15"
            ],
            [
                "MISO",
                "16"
            ],
            [
                "SCK",
                "17"
            ]
        ]
    },
    "spiClockDivide": [
        [
            "2 (8MHz)",
            "SPI_CLOCK_DIV2"
        ],
        [
            "4 (4MHz)",
            "SPI_CLOCK_DIV4"
        ],
        [
            "8 (2MHz)",
            "SPI_CLOCK_DIV8"
        ],
        [
            "16 (1MHz)",
            "SPI_CLOCK_DIV16"
        ],
        [
            "32 (500KHz)",
            "SPI_CLOCK_DIV32"
        ],
        [
            "64 (250KHz)",
            "SPI_CLOCK_DIV64"
        ],
        [
            "128 (125KHz)",
            "SPI_CLOCK_DIV128"
        ]
    ],
    "i2c": [
        [
            "I2C",
            "Wire"
        ]
    ],
    "i2cPins": {
        "Wire": [
            [
                "SDA",
                "1"
            ],
            [
                "SCL",
                "2"
            ]
        ]
    },
    "i2cSpeed": [
        [
            "100kHz",
            "100000L"
        ],
        [
            "400kHz",
            "400000L"
        ]
    ],
    "builtinLed": [
        [
            "BUILTIN_LED",
            "21"
        ]
    ],
    "interruptPins": [
        [
            "D2 (IO3)",
            "3"
        ],
        [
            "D3 (IO38)",
            "38"
        ],
        [
            "D6 (IO18)",
            "18"
        ],
        [
            "D7 (IO9)",
            "9"
        ],
        [
            "D12 (IO12)",
            "12"
        ],
        [
            "D13 (IO21)",
            "21"
        ],
        [
            "D14 (IO47)",
            "47"
        ],
        [
            "IO0",
            "0"
        ],
        [
            "IO1 (SDA)",
            "1"
        ],
        [
            "IO2 (SCL)",
            "2"
        ],
        [
            "IO3",
            "3"
        ],
        [
            "IO4",
            "4"
        ],
        [
            "IO5",
            "5"
        ],
        [
            "IO6",
            "6"
        ],
        [
            "IO7",
            "7"
        ],
        [
            "IO8",
            "8"
        ],
        [
            "IO9",
            "9"
        ],
        [
            "IO10",
            "10"
        ],
        [
            "IO11",
            "11"
        ],
        [
            "IO12",
            "12"
        ],
        [
            "IO13",
            "13"
        ],
        [
            "IO14",
            "14"
        ],
        [
            "IO15 (MOSI)",
            "15"
        ],
        [
            "IO16 (MISO)",
            "16"
        ],
        [
            "IO17 (SCK)",
            "17"
        ],
        [
            "IO18",
            "18"
        ],
        [
            "IO21",
            "21"
        ],
        [
            "IO38",
            "38"
        ],
        [
            "IO43 (TX)",
            "43"
        ],
        [
            "IO44 (RX)",
            "44"
        ],
        [
            "IO47",
            "47"
        ]
    ],
    "interruptMode": [
        [
            "LOW",
            "LOW"
        ],
        [
            "RISING",
            "RISING"
        ],
        [
            "FALLING",
            "FALLING"
        ],
        [
            "CHANGE",
            "CHANGE"
        ]
    ]
}